{
    "$schema": "http://schema.management.azure.com/schemas/2014-04-01-preview/deploymentTemplate.json#",
    "contentVersion": "1.0.0.0",
    "parameters": {
        "name": {
            "type": "string"
        },
        "APPINSIGHTS_INSTRUMENTATIONKEY": {
            "type": "string",
            "defaultValue": ""
        },
        "NODE_ENV": {
            "type": "string"
        },
        "API_ENDPOINT_URL": {
            "type": "string"
        },
        "USE_API_GATEWAY_AUTH": {
            "type": "string"
        },
        "NOMS_TOKEN": {
            "type": "secureString"
        },
        "NOMS_PRIVATE_KEY": {
            "type": "secureString"
        },
        "GOOGLE_ANALTICS_ID": {
            "type": "secureString"
        },
        "SESSION_SECRET": {
            "type": "secureString"
        }
    },
    "resources": [
        {
            "apiVersion": "2015-08-01",
            "name": "[concat(parameters('name'), '/appsettings')]",
            "type": "Microsoft.Web/sites/config",
            "properties": {
                "WEBSITE_NODE_DEFAULT_VERSION": "6.10.0",
                "APPINSIGHTS_INSTRUMENTATIONKEY": "[parameters('APPINSIGHTS_INSTRUMENTATIONKEY')]",
                "NODE_ENV": "[parameters('NODE_ENV')]",
                "API_ENDPOINT_URL": "[parameters('API_ENDPOINT_URL')]",
                "USE_API_GATEWAY_AUTH": "[parameters('USE_API_GATEWAY_AUTH')]",
                "NOMS_TOKEN": "[parameters('NOMS_TOKEN')]",
                "NOMS_PRIVATE_KEY": "[parameters('NOMS_PRIVATE_KEY')]",
                "GOOGLE_ANALYTICS_ID": "[parameters('GOOGLE_ANALYTICS_ID')]",
                "SESSION_SECRET": "[parameters('SESSION_SECRET')]"
            }
        }
    ]
}
